image_packer/__init__.py
image_packer/blf.py
image_packer/blf_solver.py
image_packer/packer.py
image_packer/tools.py
image_packer/version.py
image_packer/cli/__init__.py
image_packer/cli/pack.py
image_packer-0.9.0.dist-info/METADATA
image_packer-0.9.0.dist-info/RECORD
image_packer-0.9.0.dist-info/WHEEL
image_packer-0.9.0.dist-info/entry_points.txt
image_packer-0.9.0.dist-info/top_level.txt
