Metadata-Version: 2.1
Name: image-packer
Version: 0.9.0
Summary: Pack multiple images of different sizes or formats into one image.
Home-page: https://github.com/Hasenpfote/
Author: Hasenpfote
Author-email: Hasenpfote36@gmail.com
License: UNKNOWN
Keywords: packing,rectangle-packing
Platform: UNKNOWN
Classifier: Programming Language :: Python
Classifier: Programming Language :: Python :: 3
Classifier: Programming Language :: Python :: 3.4
Classifier: Programming Language :: Python :: 3.5
Classifier: Programming Language :: Python :: 3.6
Classifier: Programming Language :: Python :: 3.7
Classifier: License :: OSI Approved :: MIT License
Classifier: Operating System :: OS Independent
Classifier: Development Status :: 5 - Production/Stable
Classifier: Environment :: Other Environment
Classifier: Intended Audience :: Developers
Classifier: Topic :: Software Development :: Libraries :: Python Modules
Requires-Python: >=3.4
Requires-Dist: Pillow (>=5.0.0)
